pilott/__init__.py
pilott/agent/__init__.py
pilott/agent/action_agent.py
pilott/agent/agent.py
pilott/agent/master_agent.py
pilott/agent/super_agent.py
pilott/config/config.py
pilott/config/model.py
pilott/core/__init__.py
pilott/core/base_agent.py
pilott/core/memory.py
pilott/core/router.py
pilott/core/task.py
pilott/delegation/task_delegator.py
pilott/engine/llm.py
pilott/enums/__init__.py
pilott/enums/agent_e.py
pilott/enums/health_e.py
pilott/enums/process_e.py
pilott/enums/role_e.py
pilott/enums/task_e.py
pilott/enums/tool_e.py
pilott/examples/__init__.py
pilott/examples/customer_service.py
pilott/examples/document_processing.py
pilott/examples/email_service.py
pilott/examples/marketing_expert.py
pilott/examples/research_analyst.py
pilott/examples/sales_rep.py
pilott/examples/social_media_manager.py
pilott/examples/teacher.py
pilott/examples/web_search.py
pilott/knowledge/__init__.py
pilott/knowledge/knowledge.py
pilott/knowledge/source/audio_input.py
pilott/knowledge/source/base_input.py
pilott/knowledge/source/doc_input.py
pilott/knowledge/source/image_input.py
pilott/knowledge/source/json_input.py
pilott/knowledge/source/markup_input.py
pilott/knowledge/source/stream_input.py
pilott/knowledge/source/string_input.py
pilott/knowledge/source/structured_input.py
pilott/knowledge/source/url_input.py
pilott/knowledge/source/vector_input.py
pilott/knowledge/source/video_input.py
pilott/knowledge/storage/base_storage.py
pilott/memory/enhanced_memory.py
pilott/orchestration/__init__.py
pilott/orchestration/load_balancer.py
pilott/orchestration/orchestration.py
pilott/orchestration/scaling.py
pilott/pilott.py
pilott/rules/rules.yaml
pilott/tools/__init__.py
pilott/tools/tool.py
pilott/utils/__init__.py
pilott/utils/agent_utils.py
pilott/utils/common_utils.py
pilott/utils/logger.py
pilott/utils/task_utils.py
pilott-0.2.5.dist-info/LICENSE
pilott-0.2.5.dist-info/METADATA
pilott-0.2.5.dist-info/WHEEL
pilott-0.2.5.dist-info/RECORD
