Metadata-Version: 2.3
Name: pilott
Version: 0.2.5
Summary: A powerful Python framework for building scalable multi-agent systems with built-in orchestration, LLM integration, and intelligent task processing. Features dynamic scaling, fault tolerance, and advanced load balancing.
Author: Anuj Gupta
Author-email: anuj@pilottai.com
Requires-Python: >=3.10,<4.0
Classifier: Programming Language :: Python :: 3
Classifier: Programming Language :: Python :: 3.10
Classifier: Programming Language :: Python :: 3.11
Classifier: Programming Language :: Python :: 3.12
Classifier: Programming Language :: Python :: 3.13
Requires-Dist: beautifulsoup4 (>=4.13.3,<5.0.0)
Requires-Dist: cryptography (>=44.0.1,<45.0.0)
Requires-Dist: langchain-openai (>=0.3.2,<0.4.0)
Requires-Dist: litellm (>=1.59.8,<2.0.0)
Requires-Dist: markdown (>=3.7,<4.0)
Requires-Dist: numpy (>=2.2.4,<3.0.0)
Requires-Dist: pandas (>=2.2.3,<3.0.0)
Requires-Dist: pillow (>=11.1.0,<12.0.0)
Requires-Dist: psutil (>=6.1.1,<7.0.0)
Requires-Dist: pydantic (>=2.7.1,<3.0.0)
Requires-Dist: pydantic-settings (>=2.2.1,<3.0.0)
Requires-Dist: python-docx (>=1.1.2,<2.0.0)
Requires-Dist: speechrecognition (>=3.14.2,<4.0.0)
Requires-Dist: websockets (>=14.1,<15.0)
Project-URL: Homepage, https://pilottai.com
